cryptoran/__init__.py
cryptoran/__main__.py
cryptoran/cryptoran_test.py
cryptoran/packages/Encoding.py
cryptoran/packages/Utils.py
cryptoran/packages/__init__.py
cryptoran/packages/blockcipher/AES.py
cryptoran/packages/blockcipher/BlockCipher.py
cryptoran/packages/blockcipher/DES.py
cryptoran/packages/blockcipher/Mode.py
cryptoran/packages/blockcipher/__init__.py
cryptoran/packages/keyexchange/DiffieHellman.py
cryptoran/packages/keyexchange/__init__.py
cryptoran/packages/pkc/ElGamal.py
cryptoran/packages/pkc/RSA.py
cryptoran/packages/pkc/__init__.py
cryptoran/packages/pkc/pkc.py
cryptoran/packages/signature/RSAsig.py
cryptoran/packages/signature/__init__.py
cryptoran/packages/signature/signature.py
cryptoran-0.0.4.dist-info/METADATA
cryptoran-0.0.4.dist-info/RECORD
cryptoran-0.0.4.dist-info/WHEEL
cryptoran-0.0.4.dist-info/entry_points.txt
cryptoran-0.0.4.dist-info/top_level.txt
test/AEStest.py
test/EncodingTest.py
test/__init__.py
