Metadata-Version: 2.1
Name: cryptoran
Version: 0.0.4
Summary: A Python3 based cryptographic algorithms library
Home-page: https://github.com/orancanoren/cryptoran
Author: Oran Can Oren
Author-email: orancanoren@gmail.com
License: MIT
Platform: UNKNOWN
